citadel_sdk/__init__.py
citadel_sdk/client.py
citadel_sdk-0.12.dist-info/LICENSE.txt
citadel_sdk-0.12.dist-info/METADATA
citadel_sdk-0.12.dist-info/WHEEL
citadel_sdk-0.12.dist-info/top_level.txt
citadel_sdk-0.12.dist-info/RECORD
