Metadata-Version: 2.1
Name: citadel-sdk
Version: 0.12
Summary: Citadel SDK
Home-page: https://github.com/ksatzke/citadel_sdk
Download-URL: https://github.com/ksatzke/citadel-sdk/archive/refs/tags/v_012.tar.gz
Author: Citadel authors
Author-email: ksatzke@msn.com
License: MIT
Keywords: Citadel,SDK,Machine Learning
Classifier: Development Status :: 3 - Alpha
Classifier: Intended Audience :: Developers
Classifier: Topic :: Software Development :: Build Tools
Classifier: License :: OSI Approved :: MIT License
Classifier: Programming Language :: Python :: 3
Classifier: Programming Language :: Python :: 3.4
Classifier: Programming Language :: Python :: 3.5
Classifier: Programming Language :: Python :: 3.6
Classifier: Programming Language :: Python :: 3.7
Classifier: Programming Language :: Python :: 3.8
Classifier: Programming Language :: Python :: 3.9
License-File: LICENSE.txt
Requires-Dist: urllib3
